stat_tests/__init__.py
stat_tests/z_test.py
stat_tests_marchfra-0.0.3a1.dist-info/LICENSE
stat_tests_marchfra-0.0.3a1.dist-info/METADATA
stat_tests_marchfra-0.0.3a1.dist-info/WHEEL
stat_tests_marchfra-0.0.3a1.dist-info/top_level.txt
stat_tests_marchfra-0.0.3a1.dist-info/RECORD
