Metadata-Version: 2.1
Name: stat-tests-marchfra
Version: 0.0.3a1
Summary: A package that performs statistical tests
Home-page: https://github.com/marchfra/stat-tests.git
Author: marchfra
Author-email: marchfra1@gmail.com
License: UNKNOWN
Platform: UNKNOWN
Classifier: Programming Language :: Python :: 3
Classifier: License :: OSI Approved :: MIT License
Classifier: Operating System :: OS Independent
Requires-Python: >=3.9.1
Requires-Dist: sympy
Requires-Dist: uncertainties
